noteit/__init__.py
noteit-1.1.0.dist-info/DESCRIPTION.rst
noteit-1.1.0.dist-info/METADATA
noteit-1.1.0.dist-info/RECORD
noteit-1.1.0.dist-info/WHEEL
noteit-1.1.0.dist-info/entry_points.txt
noteit-1.1.0.dist-info/metadata.json
noteit-1.1.0.dist-info/top_level.txt
