Metadata-Version: 2.0
Name: noteit
Version: 1.1.0
Summary: The tool for creating notes
Home-page: https://github.com/Krukov/noteit
Author: Dmitry Krukov
Author-email: glebov.ru@gmail.com
License: MIT
Download-URL: https://github.com/Krukov/noteit/tarball/1.1.0
Keywords: noteit note console command line messages
Platform: UNKNOWN
Classifier: Development Status :: 4 - Beta
Classifier: Environment :: Console
Classifier: Intended Audience :: Developers
Classifier: License :: OSI Approved :: MIT License
Classifier: Programming Language :: Python
Classifier: Programming Language :: Python :: 2
Classifier: Programming Language :: Python :: 2.7
Classifier: Programming Language :: Python :: 3
Classifier: Programming Language :: Python :: 3.4
Classifier: Programming Language :: Python :: 3.5
